cloverly/__init__.py
cloverly/base.py
cloverly/exceptions/__init__.py
cloverly/exceptions/base.py
cloverly/resources/__init__.py
cloverly/resources/estimate.py
cloverly/resources/offset.py
cloverly/resources/offset_types.py
cloverly/resources/purchase.py
cloverly_python_module-0.7.0.dist-info/LICENSE
cloverly_python_module-0.7.0.dist-info/METADATA
cloverly_python_module-0.7.0.dist-info/WHEEL
cloverly_python_module-0.7.0.dist-info/top_level.txt
cloverly_python_module-0.7.0.dist-info/RECORD
